os_env_injection/__init__.py
os_env_injection/_core.py
os_env_injection/_decorator.py
os_env_injection/_decorator_directives.py
os_env_injection-1.0.0.dist-info/METADATA
os_env_injection-1.0.0.dist-info/WHEEL
os_env_injection-1.0.0.dist-info/top_level.txt
os_env_injection-1.0.0.dist-info/RECORD
