Metadata-Version: 2.1
Name: os-env-injection
Version: 1.0.0
Summary: Utilities to handle OS environment variables
Author: Francesco Calcavecchia
Author-email: francesco.calcavecchia@gmail.com
License: MIT
Platform: any
Classifier: Programming Language :: Python
Classifier: Operating System :: OS Independent
Requires-Python: >=3.5
Provides-Extra: dev
Requires-Dist: black ; extra == 'dev'
Requires-Dist: pre-commit ; extra == 'dev'
Requires-Dist: pytest ; extra == 'dev'
